alttext/__init__.py
alttext/admin.py
alttext/apps.py
alttext/models.py
alttext/mezzanine/__init__.py
alttext/mezzanine/templates/admin/base_site.html
alttext/migrations/0001_initial.py
alttext/migrations/__init__.py
alttext/south_migrations/0001_initial.py
alttext/south_migrations/__init__.py
alttext/templatetags/__init__.py
alttext/templatetags/alttext_tags.py
django_alttext-1.1.2.dist-info/LICENSE
django_alttext-1.1.2.dist-info/METADATA
django_alttext-1.1.2.dist-info/WHEEL
django_alttext-1.1.2.dist-info/top_level.txt
django_alttext-1.1.2.dist-info/RECORD
