Metadata-Version: 2.1
Name: django-alttext
Version: 1.1.2
Summary: Add alt text to images
Home-page: https://github.com/unplugstudio/django-alttext
Author: Unplug Studio
Author-email: hello@unplug.studio
License: MIT
Keywords: django mezzanine
Classifier: Development Status :: 5 - Production/Stable
Classifier: Intended Audience :: Developers
Classifier: Topic :: Software Development :: Libraries
Classifier: License :: OSI Approved :: MIT License
Classifier: Programming Language :: Python :: 2
Classifier: Programming Language :: Python :: 2.7
Classifier: Programming Language :: Python :: 3
Classifier: Programming Language :: Python :: 3.6
License-File: LICENSE
Requires-Dist: django (>=1.6)
